MANIFEST.in
setup.py
django_valueinlist_filter.egg-info/PKG-INFO
django_valueinlist_filter.egg-info/SOURCES.txt
django_valueinlist_filter.egg-info/dependency_links.txt
django_valueinlist_filter.egg-info/not-zip-safe
django_valueinlist_filter.egg-info/requires.txt
django_valueinlist_filter.egg-info/top_level.txt
valueinlist_filter/__init__.py
valueinlist_filter/filter.py
valueinlist_filter/forms.py
valueinlist_filter/templates/valueinlist_filter/filter.html