Metadata-Version: 1.0
Name: django-valueinlist-filter
Version: 0.1
Summary: Queryset can be filtered by a given list on the django admin page, just like: qs.filter(field__in=[list])
Home-page: http://github.com/gzeronet/django-valueinlist-filter
Author: Chris Chen
Author-email: gzerone@gmail.com
License: BSD
Keywords: django admin,django filter query,django value in list
Platform: UNKNOWN
